deepprot/__init__.py
deepprot/version.py
deepprot/_vendor/AAdata.RData
deepprot/data/__init__.py
deepprot/data/data_loader.py
deepprot/data/dataset.py
deepprot/feat/__init__.py
deepprot/feat/blosum_indices.py
deepprot/feat/cruciani_properties.py
deepprot/feat/fasgai_vectors.py
deepprot/feat/featurizer.py
deepprot/feat/identity.py
deepprot/feat/kidera_factors.py
deepprot/feat/mswhim_scores.py
deepprot/feat/protalbert.py
deepprot/feat/protbert.py
deepprot/feat/protfp.py
deepprot/feat/prott5.py
deepprot/feat/protxlnet.py
deepprot/feat/stscales.py
deepprot/feat/tscales.py
deepprot/feat/utils.py
deepprot/feat/vhse_scales.py
deepprot/feat/zscales.py
deepprot/model/__init__.py
deepprot/model/cnn.py
deepprot/model/mlp.py
deepprot/model/model.py
deepprot/model/protein_model.py
deepprot/utils/__init__.py
deepprot/utils/constants.py
deepprot-0.12.dist-info/METADATA
deepprot-0.12.dist-info/WHEEL
deepprot-0.12.dist-info/top_level.txt
deepprot-0.12.dist-info/RECORD
